{
  "move" : {
    "nothing" :     [0.1, 0.1, 0.0, 0.8],
    "bs" :          [0.5, 0.5, 0.0, 0.0],
    "bfs" :         [0.5, 0.5, 0.0, 0.0],
    "flash" :       [0.2, 0.2, 0.0, 0.6],
    "danger" :      [-2.0, -2.0, -2.0, -2.0],
    "obstruction" : [-2.0, -2.0, -2.0, -2.0],
    "goal" :        [0.3, 0.3, 0.0, 0.4],
    "initial" :     [0.3, 0.3, 0.0, 0.4],
    "boundary" :    [0.5, 0.5, 0.0, 0.0],
    "cannot" :      [0.2, 0.2, 0.0, 0.6]
  },
  "call" : {
    "nothing" :     [0.1, 0.1, 0.8, 0.0],
    "bs" :          [0.5, 0.5, 0.0, 0.0],
    "bfs" :         [0.5, 0.5, 0.0, 0.0],
    "flash" :       [0.2, 0.2, 0.6, 0.0],
    "danger" :      [0.5, 0.5, 0.0, 0.0],
    "obstruction" : [0.5, 0.5, 0.0, 0.0],
    "goal" :        [0.05, 0.05, 0.9, 0.0],
    "initial" :     [0.4, 0.4, 0.2, 0.0],
    "boundary" :    [-2.0, -2.0, -2.0, -2.0],
    "cannot" :      [-2.0, -2.0, -2.0, -2.0] 
  },
  "structure": {
    "labels" : ["rot_L", "rot_R", "move_F", "call_F"],
    "rotation" : 90,
    "energy" : 200,
    "trait" : "estoc_COVARDE"
  }
}
